[
  {
    "CreatorId": "@moriahelizabeth",
    "VideoUrl": null,
    "VideoId": "6oXspENPMwQ",
    "VideoTitle": "My 5,000 Blob Project Continues....(Blob Universe #8)",
    "VideoDescription": "The journey continues.....Let\u0027s keep going and see how many blob characters I can add to the collection today. It\u0027s going to be a lot of sculpting, customizing, and BLOBS. \n\nCHECK OUT MY NEW MERCH: https://moriahelizabethmerch.com/\n\nWHAT I\u0027M USING (contains affiliate links)\nPosca Pens: https://amzn.to/40TgXPL\nGlossy Varnish: https://amzn.to/3mnAaKC\nTooli-Art Paint Pens: https://amzn.to/47NwSlv\nLiquitex Matte Medium: https://amzn.to/3SAy1X1\nDas Air Dry Clay: https://amzn.to/3hwUHcX\nAcrylic Paint: https://amzn.to/3V1BwqH\nWhite Puffy Paint https://amzn.to/3Rsstzp\n\n\n___UPLOAD SCHEDULE___\n\nFriday at 4:00pm ET\n\n___________WELCOME TO MY CHANNEL__________\n\nHey! my name is Moriah (pronounced muh-rye-yuh) Elizabeth and this is my channel....obviously. I\u0027m 30 and like doing creative activities (mostly painting on things), or really anything that gives me an excuse to use rainbows, sprinkles and my own cutesy characters in excess. I\u0027m heavy into editing, so my video are chalk full of sound effects, filters and lil....moments, or as we like to call them \u0022MEmes.\u0022 I paint on squishies, thrift store finds, and various other items I find. I also love to draw, traditionally and digitally. I\u0027m not the most skilled artist out here, but I like to focus on having fun with creativity and being able to laugh at my own mistakes. \n\nCURRENT SERIES:\nSquishy Makeovers: Fixing and decorating used squishies sent from my viewers\nThrift Store Makeovers: Fixing and decorating stuff I find at thrift stores/yard sales\nBake With ME: Recreating squishies I\u0027ve decorated in real life\nCreate This Book: Drawing in the prompt book that I wrote (available to purchase and follow along)\nSquishy Unboxing: Opening used squishy packages sent from viewers\nDrawings to Squishies: turning my flat drawings into squishies\nFinishing Art Ideas: Choosing art ideas from my giant list and making them happen\nSquishies I\u0027ve Been Avoiding: Painting on the squishies I DON\u0027T want to paint\n\n\nFind Products I Use (contains affiliate links):\nhttps://a.co/4XDtrmV\n\n\n____PURCHASE ME PRODUCTS____\n\nCREATE THIS BOOK:\nhttps://amzn.to/2vUerfI\n\nCREATE THIS BOOK 2:\nhttps://amzn.to/2Nx2G9f\n\nCREATE THIS BOOK 3:\nhttps://amzn.to/3OQpfEJ\n\nME Merchandise:\nhttps://moriahelizabethmerch.com/\n\nOfficial Amazon Store:\nhttps://www.amazon.com/stores/MoriahElizabeth/page/84A1B7AA-51AC-4B6B-AD8D-A20CCD5FCB47?ref_=ast_bln\n\nME Nail Polish\nslatebrands.com/menails\n\n\n____ME SOCIALS____\n\nINSTAGRAM: \nhttps://www.instagram.com/moriahelizabethofficial/\n\nTIKTOK:\nhttps://www.tiktok.com/@moriahelizabeth\n\nFACEBOOK:\nhttps://www.facebook.com/Moriah-Elizabeth-102592864903627\n\nSNAPCHAT:\nMoriahOfficial\n\nVISIT ME WEBSITE:\nhttps://www.moriahelizabeth.com/\n\n\n____CONTACT ME____\n\nFOR GENERAL QUESTIONS/COMMENTS/CONCERNS:\nFanmail@Moriah.Video\n\nFOR BUSINESS INQUIRIES/OPPORTUNITIES ONLY:\nconnect@moriah.video\n\n\n_____MAIL ME_____\n\nFor sending squishies, Letters, or general fan mail, please contact: FANMAIL@MORIAH.VIDEO to request my P.O. box address \n(must be 13\u002B to send mail)\nATTENTION: Unfortunately I can only give out my address to a small amount of people each week. This is to make sure that I get a reasonable amount of mail and can feature the maximum amount on camera. I apologize in advance if you do not recieve the address.",
    "VideoLength": 0,
    "VideoThumbnail": "https://i.ytimg.com/vi/6oXspENPMwQ/default.jpg"
  },
  {
    "CreatorId": "@moriahelizabeth",
    "VideoUrl": null,
    "VideoId": "OTrmiPaLuv4",
    "VideoTitle": "My 5,000 Blob Project Continues....(Blob Universe #7)",
    "VideoDescription": "The journey continues.....Let\u0027s keep going and see how many blob characters I can add to the collection today. It\u0027s going to be a lot of sculpting, customizing, and BLOBS. \n\nWHAT I\u0027M USING (contains affiliate links)\nPosca Pens: https://amzn.to/40TgXPL\nGlossy Varnish: https://amzn.to/3mnAaKC\nTooli-Art Paint Pens: https://amzn.to/47NwSlv\nLiquitex Matte Medium: https://amzn.to/3SAy1X1\nDas Air Dry Clay: https://amzn.to/3hwUHcX\nAcrylic Paint: https://amzn.to/3V1BwqH\nWhite Puffy Paint https://amzn.to/3Rsstzp\n\n\n___UPLOAD SCHEDULE___\n\nFriday at 4:00pm ET\n\n___________WELCOME TO MY CHANNEL__________\n\nHey! my name is Moriah (pronounced muh-rye-yuh) Elizabeth and this is my channel....obviously. I\u0027m 30 and like doing creative activities (mostly painting on things), or really anything that gives me an excuse to use rainbows, sprinkles and my own cutesy characters in excess. I\u0027m heavy into editing, so my video are chalk full of sound effects, filters and lil....moments, or as we like to call them \u0022MEmes.\u0022 I paint on squishies, thrift store finds, and various other items I find. I also love to draw, traditionally and digitally. I\u0027m not the most skilled artist out here, but I like to focus on having fun with creativity and being able to laugh at my own mistakes. \n\nCURRENT SERIES:\nSquishy Makeovers: Fixing and decorating used squishies sent from my viewers\nThrift Store Makeovers: Fixing and decorating stuff I find at thrift stores/yard sales\nBake With ME: Recreating squishies I\u0027ve decorated in real life\nCreate This Book: Drawing in the prompt book that I wrote (available to purchase and follow along)\nSquishy Unboxing: Opening used squishy packages sent from viewers\nDrawings to Squishies: turning my flat drawings into squishies\nFinishing Art Ideas: Choosing art ideas from my giant list and making them happen\nSquishies I\u0027ve Been Avoiding: Painting on the squishies I DON\u0027T want to paint\n\n\nFind Products I Use (contains affiliate links):\nhttps://a.co/4XDtrmV\n\n\n____PURCHASE ME PRODUCTS____\n\nCREATE THIS BOOK:\nhttps://amzn.to/2vUerfI\n\nCREATE THIS BOOK 2:\nhttps://amzn.to/2Nx2G9f\n\nCREATE THIS BOOK 3:\nhttps://amzn.to/3OQpfEJ\n\nME Merchandise:\nhttps://moriahelizabethmerch.com/\n\nOfficial Amazon Store:\nhttps://www.amazon.com/stores/MoriahElizabeth/page/84A1B7AA-51AC-4B6B-AD8D-A20CCD5FCB47?ref_=ast_bln\n\nME Nail Polish\nslatebrands.com/menails\n\n\n____ME SOCIALS____\n\nINSTAGRAM: \nhttps://www.instagram.com/moriahelizabethofficial/\n\nTIKTOK:\nhttps://www.tiktok.com/@moriahelizabeth\n\nFACEBOOK:\nhttps://www.facebook.com/Moriah-Elizabeth-102592864903627\n\nSNAPCHAT:\nMoriahOfficial\n\nVISIT ME WEBSITE:\nhttps://www.moriahelizabeth.com/\n\n\n____CONTACT ME____\n\nFOR GENERAL QUESTIONS/COMMENTS/CONCERNS:\nFanmail@Moriah.Video\n\nFOR BUSINESS INQUIRIES/OPPORTUNITIES ONLY:\nconnect@moriah.video\n\n\n_____MAIL ME_____\n\nFor sending squishies, Letters, or general fan mail, please contact: FANMAIL@MORIAH.VIDEO to request my P.O. box address \n(must be 13\u002B to send mail)\nATTENTION: Unfortunately I can only give out my address to a small amount of people each week. This is to make sure that I get a reasonable amount of mail and can feature the maximum amount on camera. I apologize in advance if you do not recieve the address.",
    "VideoLength": 0,
    "VideoThumbnail": "https://i.ytimg.com/vi/OTrmiPaLuv4/default.jpg"
  },
  {
    "CreatorId": "@moriahelizabeth",
    "VideoUrl": null,
    "VideoId": "xMhFDmra3lA",
    "VideoTitle": "My Kid Chooses What I Paint",
    "VideoDescription": "ORDER THE ME GUIDEBOOK:  https://moriahelizabethmerch.com/\n\n___UPLOAD SCHEDULE___\n\nFriday at 4:00pm ET\n\n___________WELCOME TO MY CHANNEL__________\n\nHey! my name is Moriah (pronounced muh-rye-yuh) Elizabeth and this is my channel....obviously. I\u0027m 29 and like doing creative activities (mostly painting on things), or really anything that gives me an excuse to use rainbows, sprinkles and my own cutesy characters in excess. I\u0027m heavy into editing, so my video are chalk full of sound effects, filters and lil....moments, or as we like to call them \u0022MEmes.\u0022 I paint on squishies, thrift store finds, and various other items I find. I also love to draw, traditionally and digitally. I\u0027m not the most skilled artist out here, but I like to focus on having fun with creativity and being able to laugh at my own mistakes. \n\nCURRENT SERIES:\nSquishy Makeovers: Fixing and decorating used squishies sent from my viewers\nThrift Store Makeovers: Fixing and decorating stuff I find at thrift stores/yard sales\nBake With ME: Recreating squishies I\u0027ve decorated in real life\nCreate This Book: Drawing in the prompt book that I wrote (available to purchase and follow along)\nSquishy Unboxing: Opening used squishy packages sent from viewers\nDrawings to Squishies: turning my flat drawings into squishies\nFinishing Art Ideas: Choosing art ideas from my giant list and making them happen\nSquishies I\u0027ve Been Avoiding: Painting on the squishies I DON\u0027T want to paint\n\n\nFind Products I Use (contains affiliate links):\nhttps://a.co/4XDtrmV\n\n\n____PURCHASE ME PRODUCTS____\n\nCREATE THIS BOOK:\nhttps://amzn.to/2vUerfI\n\nCREATE THIS BOOK 2:\nhttps://amzn.to/2Nx2G9f\n\nCREATE THIS BOOK 3:\nhttps://amzn.to/3OQpfEJ\n\nME Merchandise:\nhttps://moriahelizabethmerch.com/\n\nOfficial Amazon Store:\nhttps://www.amazon.com/stores/MoriahElizabeth/page/84A1B7AA-51AC-4B6B-AD8D-A20CCD5FCB47?ref_=ast_bln\n\nME Nail Polish\nslatebrands.com/menails\n\n\n____ME SOCIALS____\n\nINSTAGRAM: \nhttps://www.instagram.com/moriahelizabethofficial/\n\nTIKTOK:\nhttps://www.tiktok.com/@moriahelizabeth\n\nFACEBOOK:\nhttps://www.facebook.com/Moriah-Elizabeth-102592864903627\n\nSNAPCHAT:\nMoriahOfficial\n\nVISIT ME WEBSITE:\nhttps://www.moriahelizabeth.com/\n\n\n____CONTACT ME____\n\nFOR GENERAL QUESTIONS/COMMENTS/CONCERNS:\nFanmail@Moriah.Video\n\nFOR BUSINESS INQUIRIES/OPPORTUNITIES ONLY:\nconnect@moriah.video\n\n\n_____MAIL ME_____\n\nFor sending squishies, Letters, or general fan mail, please contact: FANMAIL@MORIAH.VIDEO to request my P.O. box address \n(must be 13\u002B to send mail)\nATTENTION: Unfortunately I can only give out my address to a small amount of people each week. This is to make sure that I get a reasonable amount of mail and can feature the maximum amount on camera. I apologize in advance if you do not recieve the address.",
    "VideoLength": 0,
    "VideoThumbnail": "https://i.ytimg.com/vi/xMhFDmra3lA/default.jpg"
  },
  {
    "CreatorId": "@moriahelizabeth",
    "VideoUrl": null,
    "VideoId": "nUHqnQvEERs",
    "VideoTitle": "Turning My Drawings Into SQUISHIES #4",
    "VideoDescription": "Today I am going to take some of the digital and traditional drawings  I have made of some of my favorite original characters from various other art projects and turn them into squishies! \n\nDon\u0027t Forget to pre-order the ME Advent Calendar before it sells out! \nhttps://moriahelizabethmerch.com/\n\nWHAT I\u0027M USING (contains affiliate links):\nTulip Slick Fabric Paint: https://amzn.to/3LBW6uO\nTulip Matte Fabric Paint (White): https://amzn.to/3EUlSqm\nTulip Fabric Matte Paint: https://amzn.to/3FeYJAz\nWhite Posca Fine Liner: https://amzn.to/3ZTe8k4\nFabric Hot Glue: https://amzn.to/3PQ4KZh\n\n___UPLOAD SCHEDULE___\n\nFriday at 4:00pm ET\n\n___________WELCOME TO MY CHANNEL__________\n\nHey! my name is Moriah (pronounced muh-rye-yuh) Elizabeth and this is my channel....obviously. I\u0027m 29 and like doing creative activities (mostly painting on things), or really anything that gives me an excuse to use rainbows, sprinkles and my own cutesy characters in excess. I\u0027m heavy into editing, so my video are chalk full of sound effects, filters and lil....moments, or as we like to call them \u0022MEmes.\u0022 I paint on squishies, thrift store finds, and various other items I find. I also love to draw, traditionally and digitally. I\u0027m not the most skilled artist out here, but I like to focus on having fun with creativity and being able to laugh at my own mistakes. \n\nCURRENT SERIES:\nSquishy Makeovers: Fixing and decorating used squishies sent from my viewers\nThrift Store Makeovers: Fixing and decorating stuff I find at thrift stores/yard sales\nBake With ME: Recreating squishies I\u0027ve decorated in real life\nCreate This Book: Drawing in the prompt book that I wrote (available to purchase and follow along)\nSquishy Unboxing: Opening used squishy packages sent from viewers\nDrawings to Squishies: turning my flat drawings into squishies\nFinishing Art Ideas: Choosing art ideas from my giant list and making them happen\nSquishies I\u0027ve Been Avoiding: Painting on the squishies I DON\u0027T want to paint\n\n\nFind Products I Use (contains affiliate links):\nhttps://a.co/4XDtrmV\n\n\n____PURCHASE ME PRODUCTS____\n\nCREATE THIS BOOK:\nhttps://amzn.to/2vUerfI\n\nCREATE THIS BOOK 2:\nhttps://amzn.to/2Nx2G9f\n\nCREATE THIS BOOK 3:\nhttps://amzn.to/3OQpfEJ\n\nME Merchandise:\nhttps://moriahelizabethmerch.com/\n\nOfficial Amazon Store:\nhttps://www.amazon.com/stores/MoriahElizabeth/page/84A1B7AA-51AC-4B6B-AD8D-A20CCD5FCB47?ref_=ast_bln\n\nME Nail Polish\nslatebrands.com/menails\n\n\n____ME SOCIALS____\n\nINSTAGRAM: \nhttps://www.instagram.com/moriahelizabethofficial/\n\nTIKTOK:\nhttps://www.tiktok.com/@moriahelizabeth\n\nFACEBOOK:\nhttps://www.facebook.com/Moriah-Elizabeth-102592864903627\n\nSNAPCHAT:\nMoriahOfficial\n\nVISIT ME WEBSITE:\nhttps://www.moriahelizabeth.com/\n\n\n____CONTACT ME____\n\nFOR GENERAL QUESTIONS/COMMENTS/CONCERNS:\nFanmail@Moriah.Video\n\nFOR BUSINESS INQUIRIES/OPPORTUNITIES ONLY:\nconnect@moriah.video\n\n\n_____MAIL ME_____\n\nFor sending squishies, Letters, or general fan mail, please contact: FANMAIL@MORIAH.VIDEO to request my P.O. box address \n(must be 13\u002B to send mail)\nATTENTION: Unfortunately I can only give out my address to a small amount of people each week. This is to make sure that I get a reasonable amount of mail and can feature the maximum amount on camera. I apologize in advance if you do not recieve the address.\n\n\n\n\nRANKING PAGE: https://pollunit.com/polls/rrhfvvxbxd0gflmsrivtpa\n^^^^^^^^^^^^^^^^^^^^^^^^^^^^^^^^^^^^^^^^^\nDO NOT USE RANKING PAGE BEFORE YOU HAVE WATCHED THIS VIDEO: https://youtu.be/J4iu7H7KwNg",
    "VideoLength": 0,
    "VideoThumbnail": "https://i.ytimg.com/vi/nUHqnQvEERs/default.jpg"
  },
  {
    "CreatorId": "@moriahelizabeth",
    "VideoUrl": null,
    "VideoId": "OXLv2FjD23s",
    "VideoTitle": "My TOP 10 Most Underrated Characters",
    "VideoDescription": "___UPLOAD SCHEDULE___\n\nFriday at 4:00pm ET\n\n___________WELCOME TO MY CHANNEL__________\n\nHey! my name is Moriah (pronounced muh-rye-yuh) Elizabeth and this is my channel....obviously. I\u0027m 29 and like doing creative activities (mostly painting on things), or really anything that gives me an excuse to use rainbows, sprinkles and my own cutesy characters in excess. I\u0027m heavy into editing, so my video are chalk full of sound effects, filters and lil....moments, or as we like to call them \u0022MEmes.\u0022 I paint on squishies, thrift store finds, and various other items I find. I also love to draw, traditionally and digitally. I\u0027m not the most skilled artist out here, but I like to focus on having fun with creativity and being able to laugh at my own mistakes. \n\nCURRENT SERIES:\nSquishy Makeovers: Fixing and decorating used squishies sent from my viewers\nThrift Store Makeovers: Fixing and decorating stuff I find at thrift stores/yard sales\nBake With ME: Recreating squishies I\u0027ve decorated in real life\nCreate This Book: Drawing in the prompt book that I wrote (available to purchase and follow along)\nSquishy Unboxing: Opening used squishy packages sent from viewers\nDrawings to Squishies: turning my flat drawings into squishies\nFinishing Art Ideas: Choosing art ideas from my giant list and making them happen\nSquishies I\u0027ve Been Avoiding: Painting on the squishies I DON\u0027T want to paint\n\n\nFind Products I Use (contains affiliate links):\nhttps://a.co/4XDtrmV\n\n\n____PURCHASE ME PRODUCTS____\n\nCREATE THIS BOOK:\nhttps://amzn.to/2vUerfI\n\nCREATE THIS BOOK 2:\nhttps://amzn.to/2Nx2G9f\n\nCREATE THIS BOOK 3:\nhttps://amzn.to/3OQpfEJ\n\nME Merchandise:\nhttps://moriahelizabethmerch.com/\n\nOfficial Amazon Store:\nhttps://www.amazon.com/stores/MoriahElizabeth/page/84A1B7AA-51AC-4B6B-AD8D-A20CCD5FCB47?ref_=ast_bln\n\nME Nail Polish\nslatebrands.com/menails\n\n\n____ME SOCIALS____\n\nINSTAGRAM: \nhttps://www.instagram.com/moriahelizabethofficial/\n\nTIKTOK:\nhttps://www.tiktok.com/@moriahelizabeth\n\nFACEBOOK:\nhttps://www.facebook.com/Moriah-Elizabeth-102592864903627\n\nSNAPCHAT:\nMoriahOfficial\n\nVISIT ME WEBSITE:\nhttps://www.moriahelizabeth.com/\n\n\n____CONTACT ME____\n\nFOR GENERAL QUESTIONS/COMMENTS/CONCERNS:\nFanmail@Moriah.Video\n\nFOR BUSINESS INQUIRIES/OPPORTUNITIES ONLY:\nconnect@moriah.video\n\n\n_____MAIL ME_____\n\nFor sending squishies, Letters, or general fan mail, please contact: FANMAIL@MORIAH.VIDEO to request my P.O. box address \n(must be 13\u002B to send mail)\nATTENTION: Unfortunately I can only give out my address to a small amount of people each week. This is to make sure that I get a reasonable amount of mail and can feature the maximum amount on camera. I apologize in advance if you do not recieve the address.",
    "VideoLength": 0,
    "VideoThumbnail": "https://i.ytimg.com/vi/OXLv2FjD23s/default.jpg"
  }
]